llamaserve/__init__.py
llamaserve/llamaserve.py
llamaserve/llamaserve_types.py
llamaserve/py.typed
llamaserve/settings.py
llamaserve/utils.py
londonaicentre_llama_serve-1.1.3.dist-info/licenses/LICENSE.md
londonaicentre_llama_serve-1.1.3.dist-info/METADATA
londonaicentre_llama_serve-1.1.3.dist-info/WHEEL
londonaicentre_llama_serve-1.1.3.dist-info/entry_points.txt
londonaicentre_llama_serve-1.1.3.dist-info/top_level.txt
londonaicentre_llama_serve-1.1.3.dist-info/RECORD
