Metadata-Version: 2.4
Name: londonaicentre-llama-serve
Version: 1.1.3
Summary: Serve llama models locally
Author-email: "Dr. Joe Zhang" <jzhang@nhs.net>, Martin Chapman <contact@martinchapman.co.uk>
License-Expression: LicenseRef-Proprietary
Requires-Python: >=3.12
License-File: LICENSE.md
Requires-Dist: httpx>=0.28.1
Requires-Dist: pydantic>=2.12.4
Requires-Dist: pydantic-settings>=2.11.0
Requires-Dist: tqdm>=4.67.1
Requires-Dist: vllm>=0.11.0
Dynamic: license-file
